dagster_ibis_bigquery/__init__.py
dagster_ibis_bigquery/backend_fix.py
dagster_ibis_bigquery/io_manager.py
dagster_ibis_bigquery/type_handler.py
dagster_ibis_bigquery-0.1.6.dist-info/METADATA
dagster_ibis_bigquery-0.1.6.dist-info/WHEEL
dagster_ibis_bigquery-0.1.6.dist-info/RECORD
